_kaldialign.cpython-314-aarch64-linux-gnu.so
kaldialign/__init__.py
kaldialign-0.9.3.dist-info/METADATA
kaldialign-0.9.3.dist-info/WHEEL
kaldialign-0.9.3.dist-info/top_level.txt
kaldialign-0.9.3.dist-info/RECORD
kaldialign-0.9.3.dist-info/licenses/LICENSE
